{
  "main": {
    "id": "89a371856d4bb46a",
    "type": "split",
    "children": [
      {
        "id": "70b8fc9463183371",
        "type": "tabs",
        "children": [
          {
            "id": "4b47bd29c97e68c8",
            "type": "leaf",
            "pinned": true,
            "state": {
              "type": "markdown",
              "state": {
                "file": "01 - Rough Notes/What Happens Today.md",
                "mode": "source",
                "backlinks": true,
                "source": false
              },
              "pinned": true
            }
          },
          {
            "id": "5b5c2e9050bbdbb6",
            "type": "leaf",
            "pinned": true,
            "state": {
              "type": "markdown",
              "state": {
                "file": "06 - Permanent Notes/A Plan to Start a YouTube Channel.md",
                "mode": "source",
                "backlinks": true,
                "source": false
              },
              "pinned": true
            }
          },
          {
            "id": "b81e1c64b0b31dbd",
            "type": "leaf",
            "state": {
              "type": "markdown",
              "state": {
                "file": "02 - Source Materials/Books/The Six Pillars of Self-Esteem - Nathaniel Branden.md",
                "mode": "source",
                "backlinks": true,
                "source": false
              }
            }
          }
        ],
        "currentTab": 2
      }
    ],
    "direction": "vertical"
  },
  "left": {
    "id": "208b6e5d962dd553",
    "type": "split",
    "children": [
      {
        "id": "1138faa061170385",
        "type": "tabs",
        "children": [
          {
            "id": "1439b589d3d6d0fa",
            "type": "leaf",
            "state": {
              "type": "file-explorer",
              "state": {
                "sortOrder": "alphabetical"
              }
            }
          },
          {
            "id": "955a650584ba1db5",
            "type": "leaf",
            "state": {
              "type": "search",
              "state": {
                "query": "",
                "matchingCase": false,
                "explainSearch": false,
                "collapseAll": false,
                "extraContext": false,
                "sortOrder": "alphabetical"
              }
            }
          },
          {
            "id": "dbf6034ce1f83530",
            "type": "leaf",
            "state": {
              "type": "bookmarks",
              "state": {}
            }
          }
        ]
      }
    ],
    "direction": "horizontal",
    "width": 300,
    "collapsed": true
  },
  "right": {
    "id": "59ba40aeae311396",
    "type": "split",
    "children": [
      {
        "id": "4863fc1cf1f4a0a6",
        "type": "tabs",
        "children": [
          {
            "id": "a583bd8aecb851a8",
            "type": "leaf",
            "state": {
              "type": "backlink",
              "state": {
                "file": "02 - Source Materials/Books/The Six Pillars of Self-Esteem - Nathaniel Branden.md",
                "collapseAll": false,
                "extraContext": false,
                "sortOrder": "alphabetical",
                "showSearch": false,
                "searchQuery": "",
                "backlinkCollapsed": false,
                "unlinkedCollapsed": true
              }
            }
          },
          {
            "id": "c5af7234d354b6ca",
            "type": "leaf",
            "state": {
              "type": "outgoing-link",
              "state": {
                "file": "02 - Source Materials/Books/The Six Pillars of Self-Esteem - Nathaniel Branden.md",
                "linksCollapsed": false,
                "unlinkedCollapsed": true
              }
            }
          },
          {
            "id": "7d1fd120d011d45d",
            "type": "leaf",
            "state": {
              "type": "tag",
              "state": {
                "sortOrder": "frequency",
                "useHierarchy": true
              }
            }
          },
          {
            "id": "6c66a5dbee062ef1",
            "type": "leaf",
            "state": {
              "type": "outline",
              "state": {
                "file": "02 - Source Materials/Books/The Six Pillars of Self-Esteem - Nathaniel Branden.md"
              }
            }
          }
        ]
      }
    ],
    "direction": "horizontal",
    "width": 300,
    "collapsed": true
  },
  "left-ribbon": {
    "hiddenItems": {
      "switcher:Open quick switcher": false,
      "graph:Open graph view": false,
      "canvas:Create new canvas": false,
      "daily-notes:Open today's daily note": false,
      "templates:Insert template": false,
      "command-palette:Open command palette": false
    }
  },
  "active": "b81e1c64b0b31dbd",
  "lastOpenFiles": [
    "06 - Permanent Notes/A Plan to Start a YouTube Channel.md",
    "02 - Source Materials/Books/Flow - Mihaly Csikszentmihalyi.md",
    "03 - Tags/life journey.md",
    "06 - Permanent Notes/It Is Futile, and It Is Okay.md",
    "01 - Rough Notes/What Happens Today.md",
    "06 - Permanent Notes/Work on Your Backlog One Task at a Time.md",
    "06 - Permanent Notes/Active Stillness. Waiting While Working..md",
    "06 - Permanent Notes/First Bout With React Router v6.md",
    "06 - Permanent Notes/Aim for the Impossible, so That You Know Where to Go.md",
    "06 - Permanent Notes/2024-08-19.md",
    "06 - Permanent Notes/For Once, Why Don’t I Take This Life Seriously.md",
    "02 - Source Materials/Books/Atomic Habit - James Clear.md",
    "02 - Source Materials/Books/Quiet - Susan Cain.md",
    "06 - Permanent Notes/Sharing Our Creative Works as an Introvert.md",
    "03 - Tags/introvert.md",
    "02 - Source Materials/Books/Catechism of the Catholic Church.md",
    "06 - Permanent Notes/Creativity Without Compassion Is Useless.md",
    "03 - Tags/creativity.md",
    "06 - Permanent Notes/Creative Works That “Somehow” Is Helping People.md",
    "03 - Tags/Catholicism.md",
    "06 - Permanent Notes/For the Amount of Wisdom That God Has Given Me, It Should Have Been More Than Enough.md",
    "06 - Permanent Notes/A Necessary Detachment to the Work.md",
    "02 - Source Materials/Books/Big Magic - Elizabeth Gilbert.md",
    "06 - Permanent Notes/Who I Am.md",
    "06 - Permanent Notes/The Good Fruits in the Eyes of God.md",
    "06 - Permanent Notes/CS 61A, The Structure and Interpretation of Computer Programs, UC Berkeley, Brian Harvey, Spring 2010.md",
    "ui",
    "109378242_p0.png",
    "02 - Source Materials/Video Tutorials",
    "02 - Source Materials/Books",
    "06 - Permanent Notes",
    "05 - Templates",
    "04 - Indexes",
    "03 - Tags",
    "02 - Source Materials",
    "01 - Rough Notes"
  ]
}